voxjar/__init__.py
voxjar/auth.py
voxjar/push_request.py
voxjar/transport.py
voxjar-0.5.0.dist-info/LICENSE
voxjar-0.5.0.dist-info/METADATA
voxjar-0.5.0.dist-info/WHEEL
voxjar-0.5.0.dist-info/top_level.txt
voxjar-0.5.0.dist-info/RECORD
