Metadata-Version: 2.1
Name: voxjar
Version: 0.5.0
Summary: python implementation of the Voxjar API
Home-page: https://github.com/voxjar/voxjar
Author: William Myers
Author-email: will@voxjar.com
License: Apache-2
Keywords: voxjar voxjar ai requests
Platform: UNKNOWN
Classifier: Development Status :: 4 - Beta
Classifier: Intended Audience :: Developers
Classifier: Programming Language :: Python :: 2.7
Classifier: Programming Language :: Python :: 3
Classifier: License :: OSI Approved :: Apache Software License
Requires-Python: >=2.7
Requires-Dist: gql
Requires-Dist: requests
Provides-Extra: dev
Requires-Dist: twine; extra == 'dev'
Requires-Dist: wheel; extra == 'dev'
Provides-Extra: docs
Requires-Dist: sphinx; extra == 'docs'
